manishSMS/__init__.py
manishSMS/sms.py
manishSMS-0.1.4.dist-info/LICENSE
manishSMS-0.1.4.dist-info/METADATA
manishSMS-0.1.4.dist-info/WHEEL
manishSMS-0.1.4.dist-info/entry_points.txt
manishSMS-0.1.4.dist-info/top_level.txt
manishSMS-0.1.4.dist-info/RECORD
