Metadata-Version: 2.2
Name: manishSMS
Version: 0.1.4
Summary: A School Management System
Home-page: https://github.com/Manish-Let-It-Be/manishSMS
Author: Manish Prasad
Author-email: m4manishp4prasad@gmail.com.com
Classifier: Programming Language :: Python :: 3
Classifier: License :: OSI Approved :: MIT License
Classifier: Operating System :: OS Independent
Requires-Python: >=3.6
License-File: LICENSE
Requires-Dist: tabulate
Requires-Dist: openpyxl
Dynamic: author
Dynamic: author-email
Dynamic: classifier
Dynamic: description
Dynamic: description-content-type
Dynamic: home-page
Dynamic: requires-dist
Dynamic: requires-python
Dynamic: summary
